protoparser
