Metadata-Version: 2.1
Name: proto-parser
Version: 1.2.2
Summary: A package for parsing proto files
Home-page: https://github.com/khadgarmage/protoparser
Author: xiaochun.liu
Author-email: liuxiaochun@apache.org
License: UNKNOWN
Platform: UNKNOWN
Classifier: Programming Language :: Python :: 3
Classifier: License :: OSI Approved :: Apache Software License
Classifier: Operating System :: OS Independent
Classifier: Topic :: Software Development :: Libraries :: Python Modules
